Metadata-Version: 2.1
Name: BrowserWrapper
Version: 1.0.1
Summary: A selenium driver wrapper simplifying interactions with page elements
Home-page: https://github.com/MikeFez/BrowserWrapper
Author: Michael Fessenden
Author-email: MikeFez@gmail.com
Classifier: Programming Language :: Python :: 3
Classifier: License :: OSI Approved :: MIT License
Classifier: Operating System :: OS Independent
Requires-Python: >=3.6
License-File: LICENSE
